pyfirmata/__init__.py
pyfirmata/boards.py
pyfirmata/mockup.py
pyfirmata/pyfirmata.py
pyfirmata/util.py
arduPython-1.1.3.dist-info/LICENSE
arduPython-1.1.3.dist-info/METADATA
arduPython-1.1.3.dist-info/WHEEL
arduPython-1.1.3.dist-info/top_level.txt
arduPython-1.1.3.dist-info/RECORD
